ultra_config/__init__.py
ultra_config/secrets.py
ultra_config/extensions/__init__.py
ultra_config/extensions/aws.py
ultra_config-0.6.3.dist-info/DESCRIPTION.rst
ultra_config-0.6.3.dist-info/METADATA
ultra_config-0.6.3.dist-info/RECORD
ultra_config-0.6.3.dist-info/WHEEL
ultra_config-0.6.3.dist-info/metadata.json
ultra_config-0.6.3.dist-info/top_level.txt
