Metadata-Version: 2.0
Name: ultra-config
Version: 0.6.3
Summary: An extendable configuration that enables you to configure your application via python modules, config files, environment variables and more!
Home-page: https://github.com/timmmartin19/ultra_config
Author: Tim Martin
Author-email: tim@timmartin.me
License: MIT license
Keywords: ultra_config
Platform: UNKNOWN
Classifier: Development Status :: 2 - Pre-Alpha
Classifier: Intended Audience :: Developers
Classifier: License :: OSI Approved :: MIT License
Classifier: Natural Language :: English
Classifier: Programming Language :: Python :: 2
Classifier: Programming Language :: Python :: 2.6
Classifier: Programming Language :: Python :: 2.7
Classifier: Programming Language :: Python :: 3
Classifier: Programming Language :: Python :: 3.3
Classifier: Programming Language :: Python :: 3.4
Classifier: Programming Language :: Python :: 3.5
Requires-Dist: insensitive-dict
Requires-Dist: py-env-config
Provides-Extra: aws
Requires-Dist: boto3; extra == 'aws'
